creed_sdk/__init__.py
creed_sdk/client.py
creed_sdk/errors.py
creed_sdk/types.py
creed_sdk/utils.py
creed_sdk-1.0.0.dist-info/METADATA
creed_sdk-1.0.0.dist-info/WHEEL
creed_sdk-1.0.0.dist-info/RECORD
