Metadata-Version: 2.4
Name: creed-sdk
Version: 1.0.0
Summary: Creed Space SDK - Governance infrastructure for AI agents
Project-URL: Homepage, https://creed.space
Project-URL: Documentation, https://creed.space/docs/sdk
Project-URL: Repository, https://github.com/creed-space/sdk-python
Author-email: Creed Space <support@creed.space>
License: MIT
Keywords: agents,ai,constitutional-ai,creed,governance,safety,tool-calling
Classifier: Development Status :: 4 - Beta
Classifier: Intended Audience :: Developers
Classifier: License :: OSI Approved :: MIT License
Classifier: Programming Language :: Python :: 3
Classifier: Programming Language :: Python :: 3.10
Classifier: Programming Language :: Python :: 3.11
Classifier: Programming Language :: Python :: 3.12
Classifier: Programming Language :: Python :: 3.13
Classifier: Topic :: Scientific/Engineering :: Artificial Intelligence
Classifier: Topic :: Security
Classifier: Typing :: Typed
Requires-Python: >=3.10
Requires-Dist: httpx>=0.25.0
Provides-Extra: dev
Requires-Dist: mypy>=1.0.0; extra == 'dev'
Requires-Dist: pytest-asyncio>=0.21.0; extra == 'dev'
Requires-Dist: pytest>=7.0.0; extra == 'dev'
Requires-Dist: ruff>=0.1.0; extra == 'dev'
